sakia/__init__.py
sakia/app.py
sakia/constants.py
sakia/decorators.py
sakia/errors.py
sakia/g1_license.html
sakia/helpers.py
sakia/i18n_rc.py
sakia/icons_rc.py
sakia/main.py
sakia/options.py
sakia/root_servers.yml
sakia/data/__init__.py
sakia/data/connectors/__init__.py
sakia/data/connectors/bma.py
sakia/data/connectors/node.py
sakia/data/entities/__init__.py
sakia/data/entities/app_data.py
sakia/data/entities/blockchain.py
sakia/data/entities/certification.py
sakia/data/entities/connection.py
sakia/data/entities/contact.py
sakia/data/entities/dividend.py
sakia/data/entities/identity.py
sakia/data/entities/node.py
sakia/data/entities/plugin.py
sakia/data/entities/source.py
sakia/data/entities/transaction.py
sakia/data/entities/user_parameters.py
sakia/data/files/__init__.py
sakia/data/files/app_data.py
sakia/data/files/plugins.py
sakia/data/files/root_servers.py
sakia/data/files/user_parameters.py
sakia/data/graphs/__init__.py
sakia/data/graphs/base_graph.py
sakia/data/graphs/constants.py
sakia/data/graphs/wot_graph.py
sakia/data/processors/__init__.py
sakia/data/processors/blockchain.py
sakia/data/processors/certifications.py
sakia/data/processors/connections.py
sakia/data/processors/contacts.py
sakia/data/processors/dividends.py
sakia/data/processors/identities.py
sakia/data/processors/nodes.py
sakia/data/processors/sources.py
sakia/data/processors/transactions.py
sakia/data/processors/tx_lifecycle.py
sakia/data/repositories/000_add_ud_rythm_parameters.sql
sakia/data/repositories/001_add_contacts.sql
sakia/data/repositories/002_add_sentry_property.sql
sakia/data/repositories/003_add_last_state_change_property.sql
sakia/data/repositories/004_refactor_transactions.sql
sakia/data/repositories/005_add_lass_monetary_mass.sql
sakia/data/repositories/006_add_sources_conditions_property.sql
sakia/data/repositories/007_add_sources_used_by_property.sql
sakia/data/repositories/__init__.py
sakia/data/repositories/blockchains.py
sakia/data/repositories/certifications.py
sakia-0.53.2.dist-info/LICENSE
sakia-0.53.2.dist-info/METADATA
sakia-0.53.2.dist-info/WHEEL
sakia-0.53.2.dist-info/entry_points.txt
sakia-0.53.2.dist-info/top_level.txt
sakia-0.53.2.dist-info/RECORD
