Metadata-Version: 2.1
Name: sakia
Version: 0.53.2
Summary: A [duniter](https://github.com/duniter/duniter) Python client
Home-page: https://github.com/duniter/sakia
Author: inso
Author-email: insomniak.fr@gmail.com
License: UNKNOWN
Platform: UNKNOWN
Classifier: Programming Language :: Python
Classifier: Development Status :: 4 - Beta
Classifier: License :: OSI Approved :: GNU General Public License v3 (GPLv3)
Classifier: Natural Language :: French
Classifier: Operating System :: OS Independent
Classifier: Programming Language :: Python :: 3.5
Classifier: Topic :: Communications
Requires-Dist: pypeg2
Requires-Dist: aiohttp (==3.6.2)
Requires-Dist: async-timeout (==3.0.1)
Requires-Dist: attrs (==19.3.0)
Requires-Dist: duniterpy (==0.58.1)
Requires-Dist: jsonschema (==3.2.0)
Requires-Dist: networkx (==2.4)
Requires-Dist: PyQt5 (==5.9.2)
Requires-Dist: PyYAML (==5.3)
Requires-Dist: Quamash (==0.6.1)
